tools/__init__.py
tools/main.py
tools/utils.py
taskwarrior_flow-0.5.2.dist-info/LICENSE
taskwarrior_flow-0.5.2.dist-info/METADATA
taskwarrior_flow-0.5.2.dist-info/WHEEL
taskwarrior_flow-0.5.2.dist-info/entry_points.txt
taskwarrior_flow-0.5.2.dist-info/RECORD
