Metadata-Version: 2.1
Name: taskwarrior_flow
Version: 0.5.2
Summary: Set of helpers for improving Taskwarrior workflow
Author: Ben Trinh
Author-email: huantrinh1802@gmail.com
Requires-Python: >=3.10,<4.0
Classifier: Programming Language :: Python :: 3
Classifier: Programming Language :: Python :: 3.10
Classifier: Programming Language :: Python :: 3.11
Classifier: Programming Language :: Python :: 3.12
Requires-Dist: dateparser (>=1.2.0,<2.0.0)
Requires-Dist: python-dateutil (>=2.8.2,<3.0.0)
Requires-Dist: questionary (>=2.0.1,<3.0.0)
Requires-Dist: typer (>=0.12.3,<0.13.0)
Project-URL: Homepage, https://github.com/huantrinh1802/taskwarrior_flow
Project-URL: Issues, https://github.com/huantrinh1802/taskwarrior_flow/issues
